statskita/.python-version
statskita/__init__.py
statskita/configs/sakernas/2023-02.yaml
statskita/configs/sakernas/2023-08.yaml
statskita/configs/sakernas/2024-02.yaml
statskita/configs/sakernas/2024-08.yaml
statskita/configs/sakernas/2025-02.yaml
statskita/configs/sakernas/base.yaml
statskita/configs/sakernas/defaults.yaml
statskita/core/__init__.py
statskita/core/harmonizer.py
statskita/core/indicators.py
statskita/core/multilevel.py
statskita/core/survey.py
statskita/core/wrangler.py
statskita/exporters/__init__.py
statskita/exporters/excel.py
statskita/exporters/parquet.py
statskita/exporters/stata.py
statskita/loaders/__init__.py
statskita/loaders/base.py
statskita/loaders/multi_wave.py
statskita/loaders/sakernas.py
statskita/sakernas/__init__.py
statskita/utils/__init__.py
statskita/utils/config_utils.py
statskita/utils/converters.py
statskita-0.2.0.dist-info/METADATA
statskita-0.2.0.dist-info/WHEEL
statskita-0.2.0.dist-info/licenses/LICENSE
statskita-0.2.0.dist-info/RECORD
